{
  "tasks": {
    "task00": {
      "run": 43514,
      "timer": {
        "period": 1400000,
        "mode": "absolute",
        "ref": "unique"
      },
      "dl-runtime": 47910,
      "dl-period": 1400000,
      "delay": 500000
    },
    "task01": {
      "run": 1155043,
      "timer": {
        "period": 3200000,
        "mode": "absolute",
        "ref": "unique"
      },
      "dl-runtime": 1217940,
      "dl-period": 3200000,
      "delay": 500000
    },
    "task02": {
      "run": 360482,
      "timer": {
        "period": 800000,
        "mode": "absolute",
        "ref": "unique"
      },
      "dl-runtime": 381560,
      "dl-period": 800000,
      "delay": 500000
    },
    "task03": {
      "run": 95308,
      "timer": {
        "period": 400000,
        "mode": "absolute",
        "ref": "unique"
      },
      "dl-runtime": 102430,
      "dl-period": 400000,
      "delay": 500000
    },
    "task04": {
      "run": 1072402,
      "timer": {
        "period": 1500000,
        "mode": "absolute",
        "ref": "unique"
      },
      "dl-runtime": 1130950,
      "dl-period": 1500000,
      "delay": 500000
    },
    "task05": {
      "run": 538949,
      "timer": {
        "period": 1100000,
        "mode": "absolute",
        "ref": "unique"
      },
      "dl-runtime": 569420,
      "dl-period": 1100000,
      "delay": 500000
    },
    "task06": {
      "run": 112351,
      "timer": {
        "period": 400000,
        "mode": "absolute",
        "ref": "unique"
      },
      "dl-runtime": 120370,
      "dl-period": 400000,
      "delay": 500000
    },
    "task07": {
      "run": 60405,
      "timer": {
        "period": 300000,
        "mode": "absolute",
        "ref": "unique"
      },
      "dl-runtime": 65690,
      "dl-period": 300000,
      "delay": 500000
    },
    "task08": {
      "run": 63920,
      "timer": {
        "period": 1500000,
        "mode": "absolute",
        "ref": "unique"
      },
      "dl-runtime": 69390,
      "dl-period": 1500000,
      "delay": 500000
    },
    "task09": {
      "run": 14758,
      "timer": {
        "period": 900000,
        "mode": "absolute",
        "ref": "unique"
      },
      "dl-runtime": 17640,
      "dl-period": 900000,
      "delay": 500000
    },
    "task10": {
      "run": 412038,
      "timer": {
        "period": 1500000,
        "mode": "absolute",
        "ref": "unique"
      },
      "dl-runtime": 435830,
      "dl-period": 1500000,
      "delay": 500000
    },
    "task11": {
      "run": 373687,
      "timer": {
        "period": 1300000,
        "mode": "absolute",
        "ref": "unique"
      },
      "dl-runtime": 395460,
      "dl-period": 1300000,
      "delay": 500000
    }
  },
  "global": {
    "duration": 30,
    "default_policy": "SCHED_DEADLINE",
    "calibration": 92,
    "pi_enabled": false,
    "lock_pages": true,
    "logdir": "/tmp/rt-app-logs",
    "log_basename": "rt-app",
    "log_size": "auto",
    "gnuplot": false
  }
}