{
  "tasks": {
    "task00": {
      "run": 14644,
      "timer": {
        "period": 1200000,
        "mode": "absolute",
        "ref": "unique"
      },
      "dl-runtime": 17520,
      "dl-period": 1200000,
      "delay": 500000
    },
    "task01": {
      "run": 155367,
      "timer": {
        "period": 1300000,
        "mode": "absolute",
        "ref": "unique"
      },
      "dl-runtime": 165650,
      "dl-period": 1300000,
      "delay": 500000
    },
    "task02": {
      "run": 17817,
      "timer": {
        "period": 300000,
        "mode": "absolute",
        "ref": "unique"
      },
      "dl-runtime": 20860,
      "dl-period": 300000,
      "delay": 500000
    },
    "task03": {
      "run": 452575,
      "timer": {
        "period": 1200000,
        "mode": "absolute",
        "ref": "unique"
      },
      "dl-runtime": 478500,
      "dl-period": 1200000,
      "delay": 500000
    },
    "task04": {
      "run": 17807,
      "timer": {
        "period": 300000,
        "mode": "absolute",
        "ref": "unique"
      },
      "dl-runtime": 20850,
      "dl-period": 300000,
      "delay": 500000
    },
    "task05": {
      "run": 80526,
      "timer": {
        "period": 500000,
        "mode": "absolute",
        "ref": "unique"
      },
      "dl-runtime": 86870,
      "dl-period": 500000,
      "delay": 500000
    },
    "task06": {
      "run": 172743,
      "timer": {
        "period": 3800000,
        "mode": "absolute",
        "ref": "unique"
      },
      "dl-runtime": 183940,
      "dl-period": 3800000,
      "delay": 500000
    },
    "task07": {
      "run": 35259,
      "timer": {
        "period": 400000,
        "mode": "absolute",
        "ref": "unique"
      },
      "dl-runtime": 39220,
      "dl-period": 400000,
      "delay": 500000
    }
  },
  "global": {
    "duration": 30,
    "default_policy": "SCHED_DEADLINE",
    "calibration": 92,
    "pi_enabled": false,
    "lock_pages": true,
    "logdir": "/tmp/rt-app-logs",
    "log_basename": "rt-app",
    "log_size": "auto",
    "gnuplot": false
  }
}