{
  "tasks": {
    "task00": {
      "run": 87186,
      "timer": {
        "period": 140000,
        "mode": "absolute",
        "ref": "unique"
      },
      "dl-runtime": 91775,
      "dl-period": 140000,
      "delay": 500000
    },
    "task01": {
      "run": 95863,
      "timer": {
        "period": 110000,
        "mode": "absolute",
        "ref": "unique"
      },
      "dl-runtime": 100909,
      "dl-period": 110000,
      "delay": 500000
    },
    "task02": {
      "run": 42316,
      "timer": {
        "period": 70000,
        "mode": "absolute",
        "ref": "unique"
      },
      "dl-runtime": 44544,
      "dl-period": 70000,
      "delay": 500000
    },
    "task03": {
      "run": 118420,
      "timer": {
        "period": 150000,
        "mode": "absolute",
        "ref": "unique"
      },
      "dl-runtime": 124653,
      "dl-period": 150000,
      "delay": 500000
    },
    "task04": {
      "run": 48589,
      "timer": {
        "period": 130000,
        "mode": "absolute",
        "ref": "unique"
      },
      "dl-runtime": 51147,
      "dl-period": 130000,
      "delay": 500000
    },
    "task05": {
      "run": 5059,
      "timer": {
        "period": 20000,
        "mode": "absolute",
        "ref": "unique"
      },
      "dl-runtime": 5326,
      "dl-period": 20000,
      "delay": 500000
    }
  },
  "global": {
    "duration": 300,
    "default_policy": "SCHED_DEADLINE",
    "calibration": 80,
    "pi_enabled": false,
    "lock_pages": true,
    "logdir": "/tmp/rt-app-logs",
    "log_basename": "rt-app",
    "log_size": "auto",
    "gnuplot": false
  }
}