{
  "tasks": {
    "task00": {
      "run": 43945,
      "timer": {
        "period": 270000,
        "mode": "absolute",
        "ref": "unique"
      },
      "dl-runtime": 46258,
      "dl-period": 270000,
      "delay": 500000
    },
    "task01": {
      "run": 18227,
      "timer": {
        "period": 90000,
        "mode": "absolute",
        "ref": "unique"
      },
      "dl-runtime": 19187,
      "dl-period": 90000,
      "delay": 500000
    },
    "task02": {
      "run": 1049,
      "timer": {
        "period": 680000,
        "mode": "absolute",
        "ref": "unique"
      },
      "dl-runtime": 1105,
      "dl-period": 680000,
      "delay": 500000
    },
    "task03": {
      "run": 4714,
      "timer": {
        "period": 30000,
        "mode": "absolute",
        "ref": "unique"
      },
      "dl-runtime": 4963,
      "dl-period": 30000,
      "delay": 500000
    },
    "task04": {
      "run": 2412,
      "timer": {
        "period": 60000,
        "mode": "absolute",
        "ref": "unique"
      },
      "dl-runtime": 2539,
      "dl-period": 60000,
      "delay": 500000
    },
    "task05": {
      "run": 73961,
      "timer": {
        "period": 140000,
        "mode": "absolute",
        "ref": "unique"
      },
      "dl-runtime": 77854,
      "dl-period": 140000,
      "delay": 500000
    }
  },
  "global": {
    "duration": 128,
    "default_policy": "SCHED_DEADLINE",
    "calibration": 80,
    "pi_enabled": false,
    "lock_pages": true,
    "logdir": "/tmp/rt-app-logs",
    "log_basename": "rt-app",
    "log_size": "auto",
    "gnuplot": false
  }
}