{
  "tasks": {
    "task00": {
      "run": 3536,
      "timer": {
        "period": 30000,
        "mode": "absolute",
        "ref": "unique"
      },
      "dl-runtime": 5536,
      "dl-period": 30000,
      "delay": 500000
    },
    "task01": {
      "run": 55802,
      "timer": {
        "period": 160000,
        "mode": "absolute",
        "ref": "unique"
      },
      "dl-runtime": 58739,
      "dl-period": 160000,
      "delay": 500000
    },
    "task02": {
      "run": 103377,
      "timer": {
        "period": 130000,
        "mode": "absolute",
        "ref": "unique"
      },
      "dl-runtime": 108818,
      "dl-period": 130000,
      "delay": 500000
    },
    "task03": {
      "run": 80623,
      "timer": {
        "period": 130000,
        "mode": "absolute",
        "ref": "unique"
      },
      "dl-runtime": 84867,
      "dl-period": 130000,
      "delay": 500000
    },
    "task04": {
      "run": 251768,
      "timer": {
        "period": 290000,
        "mode": "absolute",
        "ref": "unique"
      },
      "dl-runtime": 265019,
      "dl-period": 290000,
      "delay": 500000
    },
    "task05": {
      "run": 20016,
      "timer": {
        "period": 90000,
        "mode": "absolute",
        "ref": "unique"
      },
      "dl-runtime": 22016,
      "dl-period": 90000,
      "delay": 500000
    }
  },
  "global": {
    "duration": 30,
    "default_policy": "SCHED_DEADLINE",
    "calibration": 92,
    "pi_enabled": false,
    "lock_pages": true,
    "logdir": "/tmp/rt-app-logs",
    "log_basename": "rt-app",
    "log_size": "auto",
    "gnuplot": false
  }
}