{
  "tasks": {
    "task00": {
      "run": 19498,
      "timer": {
        "period": 500000,
        "mode": "absolute",
        "ref": "unique"
      },
      "dl-runtime": 22630,
      "dl-period": 500000,
      "delay": 500000
    },
    "task01": {
      "run": 378066,
      "timer": {
        "period": 1300000,
        "mode": "absolute",
        "ref": "unique"
      },
      "dl-runtime": 400070,
      "dl-period": 1300000,
      "delay": 500000
    },
    "task02": {
      "run": 207579,
      "timer": {
        "period": 300000,
        "mode": "absolute",
        "ref": "unique"
      },
      "dl-runtime": 220610,
      "dl-period": 300000,
      "delay": 500000
    },
    "task03": {
      "run": 663418,
      "timer": {
        "period": 1200000,
        "mode": "absolute",
        "ref": "unique"
      },
      "dl-runtime": 700440,
      "dl-period": 1200000,
      "delay": 500000
    },
    "task04": {
      "run": 59408,
      "timer": {
        "period": 300000,
        "mode": "absolute",
        "ref": "unique"
      },
      "dl-runtime": 64640,
      "dl-period": 300000,
      "delay": 500000
    },
    "task05": {
      "run": 179060,
      "timer": {
        "period": 500000,
        "mode": "absolute",
        "ref": "unique"
      },
      "dl-runtime": 190590,
      "dl-period": 500000,
      "delay": 500000
    },
    "task06": {
      "run": 539709,
      "timer": {
        "period": 3800000,
        "mode": "absolute",
        "ref": "unique"
      },
      "dl-runtime": 570220,
      "dl-period": 3800000,
      "delay": 500000
    },
    "task07": {
      "run": 256856,
      "timer": {
        "period": 400000,
        "mode": "absolute",
        "ref": "unique"
      },
      "dl-runtime": 272480,
      "dl-period": 400000,
      "delay": 500000
    }
  },
  "global": {
    "duration": 30,
    "default_policy": "SCHED_DEADLINE",
    "calibration": 92,
    "pi_enabled": false,
    "lock_pages": true,
    "logdir": "/tmp/rt-app-logs",
    "log_basename": "rt-app",
    "log_size": "auto",
    "gnuplot": false
  }
}