{
  "tasks": {
    "task00": {
      "run": 37548,
      "timer": {
        "period": 300000,
        "mode": "absolute",
        "ref": "unique"
      },
      "dl-runtime": 41630,
      "dl-period": 300000,
      "delay": 500000
    },
    "task01": {
      "run": 20809,
      "timer": {
        "period": 200000,
        "mode": "absolute",
        "ref": "unique"
      },
      "dl-runtime": 24010,
      "dl-period": 200000,
      "delay": 500000
    },
    "task02": {
      "run": 81277,
      "timer": {
        "period": 1600000,
        "mode": "absolute",
        "ref": "unique"
      },
      "dl-runtime": 87660,
      "dl-period": 1600000,
      "delay": 500000
    },
    "task03": {
      "run": 745137,
      "timer": {
        "period": 1400000,
        "mode": "absolute",
        "ref": "unique"
      },
      "dl-runtime": 786460,
      "dl-period": 1400000,
      "delay": 500000
    },
    "task04": {
      "run": 263344,
      "timer": {
        "period": 1700000,
        "mode": "absolute",
        "ref": "unique"
      },
      "dl-runtime": 279310,
      "dl-period": 1700000,
      "delay": 500000
    },
    "task05": {
      "run": 20211,
      "timer": {
        "period": 400000,
        "mode": "absolute",
        "ref": "unique"
      },
      "dl-runtime": 23380,
      "dl-period": 400000,
      "delay": 500000
    },
    "task06": {
      "run": 68205,
      "timer": {
        "period": 500000,
        "mode": "absolute",
        "ref": "unique"
      },
      "dl-runtime": 73900,
      "dl-period": 500000,
      "delay": 500000
    },
    "task07": {
      "run": 189548,
      "timer": {
        "period": 400000,
        "mode": "absolute",
        "ref": "unique"
      },
      "dl-runtime": 201630,
      "dl-period": 400000,
      "delay": 500000
    }
  },
  "global": {
    "duration": 30,
    "default_policy": "SCHED_DEADLINE",
    "calibration": 92,
    "pi_enabled": false,
    "lock_pages": true,
    "logdir": "/tmp/rt-app-logs",
    "log_basename": "rt-app",
    "log_size": "auto",
    "gnuplot": false
  }
}