{
  "tasks": {
    "task00": {
      "run": 164145,
      "timer": {
        "period": 1200000,
        "mode": "absolute",
        "ref": "unique"
      },
      "dl-runtime": 174890,
      "dl-period": 1200000,
      "delay": 500000
    },
    "task01": {
      "run": 980366,
      "timer": {
        "period": 2400000,
        "mode": "absolute",
        "ref": "unique"
      },
      "dl-runtime": 1034070,
      "dl-period": 2400000,
      "delay": 500000
    },
    "task02": {
      "run": 304821,
      "timer": {
        "period": 900000,
        "mode": "absolute",
        "ref": "unique"
      },
      "dl-runtime": 322970,
      "dl-period": 900000,
      "delay": 500000
    },
    "task03": {
      "run": 938918,
      "timer": {
        "period": 3700000,
        "mode": "absolute",
        "ref": "unique"
      },
      "dl-runtime": 990440,
      "dl-period": 3700000,
      "delay": 500000
    },
    "task04": {
      "run": 17047,
      "timer": {
        "period": 3600000,
        "mode": "absolute",
        "ref": "unique"
      },
      "dl-runtime": 20050,
      "dl-period": 3600000,
      "delay": 500000
    },
    "task05": {
      "run": 10255,
      "timer": {
        "period": 200000,
        "mode": "absolute",
        "ref": "unique"
      },
      "dl-runtime": 12900,
      "dl-period": 200000,
      "delay": 500000
    },
    "task06": {
      "run": 11309,
      "timer": {
        "period": 200000,
        "mode": "absolute",
        "ref": "unique"
      },
      "dl-runtime": 14010,
      "dl-period": 200000,
      "delay": 500000
    },
    "task07": {
      "run": 26557,
      "timer": {
        "period": 300000,
        "mode": "absolute",
        "ref": "unique"
      },
      "dl-runtime": 30060,
      "dl-period": 300000,
      "delay": 500000
    },
    "task08": {
      "run": 184399,
      "timer": {
        "period": 2200000,
        "mode": "absolute",
        "ref": "unique"
      },
      "dl-runtime": 196210,
      "dl-period": 2200000,
      "delay": 500000
    },
    "task09": {
      "run": 75738,
      "timer": {
        "period": 300000,
        "mode": "absolute",
        "ref": "unique"
      },
      "dl-runtime": 81830,
      "dl-period": 300000,
      "delay": 500000
    },
    "task10": {
      "run": 271315,
      "timer": {
        "period": 1200000,
        "mode": "absolute",
        "ref": "unique"
      },
      "dl-runtime": 287700,
      "dl-period": 1200000,
      "delay": 500000
    },
    "task11": {
      "run": 13276,
      "timer": {
        "period": 3300000,
        "mode": "absolute",
        "ref": "unique"
      },
      "dl-runtime": 16080,
      "dl-period": 3300000,
      "delay": 500000
    }
  },
  "global": {
    "duration": 30,
    "default_policy": "SCHED_DEADLINE",
    "calibration": 92,
    "pi_enabled": false,
    "lock_pages": true,
    "logdir": "/tmp/rt-app-logs",
    "log_basename": "rt-app",
    "log_size": "auto",
    "gnuplot": false
  }
}