{
  "tasks": {
    "task00": {
      "run": 25924,
      "timer": {
        "period": 100000,
        "mode": "absolute",
        "ref": "unique"
      },
      "dl-runtime": 27289,
      "dl-period": 100000,
      "delay": 500000
    },
    "task01": {
      "run": 33878,
      "timer": {
        "period": 250000,
        "mode": "absolute",
        "ref": "unique"
      },
      "dl-runtime": 35662,
      "dl-period": 250000,
      "delay": 500000
    },
    "task02": {
      "run": 90159,
      "timer": {
        "period": 200000,
        "mode": "absolute",
        "ref": "unique"
      },
      "dl-runtime": 94905,
      "dl-period": 200000,
      "delay": 500000
    },
    "task03": {
      "run": 12547,
      "timer": {
        "period": 60000,
        "mode": "absolute",
        "ref": "unique"
      },
      "dl-runtime": 13208,
      "dl-period": 60000,
      "delay": 500000
    },
    "task04": {
      "run": 45104,
      "timer": {
        "period": 160000,
        "mode": "absolute",
        "ref": "unique"
      },
      "dl-runtime": 47478,
      "dl-period": 160000,
      "delay": 500000
    },
    "task05": {
      "run": 1325,
      "timer": {
        "period": 3990000,
        "mode": "absolute",
        "ref": "unique"
      },
      "dl-runtime": 1395,
      "dl-period": 3990000,
      "delay": 500000
    },
    "task06": {
      "run": 10015,
      "timer": {
        "period": 100000,
        "mode": "absolute",
        "ref": "unique"
      },
      "dl-runtime": 10543,
      "dl-period": 100000,
      "delay": 500000
    },
    "task07": {
      "run": 16782,
      "timer": {
        "period": 140000,
        "mode": "absolute",
        "ref": "unique"
      },
      "dl-runtime": 17666,
      "dl-period": 140000,
      "delay": 500000
    },
    "task08": {
      "run": 2540,
      "timer": {
        "period": 20000,
        "mode": "absolute",
        "ref": "unique"
      },
      "dl-runtime": 2674,
      "dl-period": 20000,
      "delay": 500000
    },
    "task09": {
      "run": 27041,
      "timer": {
        "period": 120000,
        "mode": "absolute",
        "ref": "unique"
      },
      "dl-runtime": 28465,
      "dl-period": 120000,
      "delay": 500000
    },
    "task10": {
      "run": 1597,
      "timer": {
        "period": 120000,
        "mode": "absolute",
        "ref": "unique"
      },
      "dl-runtime": 1682,
      "dl-period": 120000,
      "delay": 500000
    },
    "task11": {
      "run": 1490,
      "timer": {
        "period": 60000,
        "mode": "absolute",
        "ref": "unique"
      },
      "dl-runtime": 1569,
      "dl-period": 60000,
      "delay": 500000
    }
  },
  "global": {
    "duration": 600,
    "default_policy": "SCHED_DEADLINE",
    "calibration": 80,
    "pi_enabled": false,
    "lock_pages": true,
    "logdir": "/tmp/rt-app-logs",
    "log_basename": "rt-app",
    "log_size": "auto",
    "gnuplot": false
  }
}