{
  "tasks": {
    "task00": {
      "run": 138837,
      "timer": {
        "period": 210000,
        "mode": "absolute",
        "ref": "unique"
      },
      "dl-runtime": 146145,
      "dl-period": 210000,
      "delay": 500000
    },
    "task01": {
      "run": 45337,
      "timer": {
        "period": 90000,
        "mode": "absolute",
        "ref": "unique"
      },
      "dl-runtime": 47724,
      "dl-period": 90000,
      "delay": 500000
    },
    "task02": {
      "run": 82838,
      "timer": {
        "period": 90000,
        "mode": "absolute",
        "ref": "unique"
      },
      "dl-runtime": 87198,
      "dl-period": 90000,
      "delay": 500000
    },
    "task03": {
      "run": 144902,
      "timer": {
        "period": 480000,
        "mode": "absolute",
        "ref": "unique"
      },
      "dl-runtime": 152529,
      "dl-period": 480000,
      "delay": 500000
    },
    "task04": {
      "run": 24991,
      "timer": {
        "period": 60000,
        "mode": "absolute",
        "ref": "unique"
      },
      "dl-runtime": 26991,
      "dl-period": 60000,
      "delay": 500000
    },
    "task05": {
      "run": 181827,
      "timer": {
        "period": 930000,
        "mode": "absolute",
        "ref": "unique"
      },
      "dl-runtime": 191397,
      "dl-period": 930000,
      "delay": 500000
    },
    "task06": {
      "run": 11020,
      "timer": {
        "period": 60000,
        "mode": "absolute",
        "ref": "unique"
      },
      "dl-runtime": 13020,
      "dl-period": 60000,
      "delay": 500000
    },
    "task07": {
      "run": 3217,
      "timer": {
        "period": 360000,
        "mode": "absolute",
        "ref": "unique"
      },
      "dl-runtime": 5217,
      "dl-period": 360000,
      "delay": 500000
    }
  },
  "global": {
    "duration": 30,
    "default_policy": "SCHED_DEADLINE",
    "calibration": 92,
    "pi_enabled": false,
    "lock_pages": true,
    "logdir": "/tmp/rt-app-logs",
    "log_basename": "rt-app",
    "log_size": "auto",
    "gnuplot": false
  }
}