{
  "tasks": {
    "task00": {
      "run": 267497,
      "timer": {
        "period": 350000,
        "mode": "absolute",
        "ref": "unique"
      },
      "dl-runtime": 281576,
      "dl-period": 350000,
      "delay": 500000
    },
    "task01": {
      "run": 76874,
      "timer": {
        "period": 660000,
        "mode": "absolute",
        "ref": "unique"
      },
      "dl-runtime": 80920,
      "dl-period": 660000,
      "delay": 500000
    },
    "task02": {
      "run": 527299,
      "timer": {
        "period": 620000,
        "mode": "absolute",
        "ref": "unique"
      },
      "dl-runtime": 555052,
      "dl-period": 620000,
      "delay": 500000
    },
    "task03": {
      "run": 164478,
      "timer": {
        "period": 260000,
        "mode": "absolute",
        "ref": "unique"
      },
      "dl-runtime": 173135,
      "dl-period": 260000,
      "delay": 500000
    },
    "task04": {
      "run": 77275,
      "timer": {
        "period": 170000,
        "mode": "absolute",
        "ref": "unique"
      },
      "dl-runtime": 81343,
      "dl-period": 170000,
      "delay": 500000
    },
    "task05": {
      "run": 201680,
      "timer": {
        "period": 490000,
        "mode": "absolute",
        "ref": "unique"
      },
      "dl-runtime": 212295,
      "dl-period": 490000,
      "delay": 500000
    }
  },
  "global": {
    "duration": 30,
    "default_policy": "SCHED_DEADLINE",
    "calibration": 92,
    "pi_enabled": false,
    "lock_pages": true,
    "logdir": "/tmp/rt-app-logs",
    "log_basename": "rt-app",
    "log_size": "auto",
    "gnuplot": false
  }
}