{
  "tasks": {
    "task00": {
      "run": 482319,
      "timer": {
        "period": 1000000,
        "mode": "absolute",
        "ref": "unique"
      },
      "dl-runtime": 509810,
      "dl-period": 1000000,
      "delay": 500000
    },
    "task01": {
      "run": 14064,
      "timer": {
        "period": 200000,
        "mode": "absolute",
        "ref": "unique"
      },
      "dl-runtime": 16910,
      "dl-period": 200000,
      "delay": 500000
    },
    "task02": {
      "run": 1017502,
      "timer": {
        "period": 1100000,
        "mode": "absolute",
        "ref": "unique"
      },
      "dl-runtime": 1073160,
      "dl-period": 1100000,
      "delay": 500000
    },
    "task03": {
      "run": 411962,
      "timer": {
        "period": 1100000,
        "mode": "absolute",
        "ref": "unique"
      },
      "dl-runtime": 435750,
      "dl-period": 1100000,
      "delay": 500000
    },
    "task04": {
      "run": 431618,
      "timer": {
        "period": 900000,
        "mode": "absolute",
        "ref": "unique"
      },
      "dl-runtime": 456440,
      "dl-period": 900000,
      "delay": 500000
    },
    "task05": {
      "run": 484495,
      "timer": {
        "period": 1200000,
        "mode": "absolute",
        "ref": "unique"
      },
      "dl-runtime": 512100,
      "dl-period": 1200000,
      "delay": 500000
    }
  },
  "global": {
    "duration": 30,
    "default_policy": "SCHED_DEADLINE",
    "calibration": 92,
    "pi_enabled": false,
    "lock_pages": true,
    "logdir": "/tmp/rt-app-logs",
    "log_basename": "rt-app",
    "log_size": "auto",
    "gnuplot": false
  }
}